<?xml version="1.0" encoding="utf-8" ?>
<Defs>
	<ThoughtDef>
		<defName>QE_CrudeBionics</defName>
		<workerClass>QEthics.ThoughtWorker_HasCrudeAddedBodyPart</workerClass>
		<validWhileDespawned>true</validWhileDespawned>
		<stages>
			<li>
				<label>one crude bionic</label>
				<description>The chafing from this bionic is pretty uncomfortable.</description>
				<baseMoodEffect>-5</baseMoodEffect>
			</li>
			<li>
				<label>two crude bionics</label>
				<description>I do not like these chafing bionics.</description>
				<baseMoodEffect>-10</baseMoodEffect>
			</li>
			<li>
				<label>three crude bionics</label>
				<description>Ugh... Will it never end? I do not like these bionics.</description>
				<baseMoodEffect>-15</baseMoodEffect>
			</li>
			<li>
				<label>four crude bionics</label>
				<description>This is a torturous existence.</description>
				<baseMoodEffect>-20</baseMoodEffect>
			</li>
			<li>
				<label>five crude bionics</label>
				<description>The pain, itching and chafing never ends!</description>
				<baseMoodEffect>-25</baseMoodEffect>
			</li>
			<li>
				<label>six crude bionics</label>
				<description>These bionics are driving me mad!</description>
				<baseMoodEffect>-30</baseMoodEffect>
			</li>
			<li>
				<label>seven crude bionics</label>
				<description>AHHH! Take them out! TAKE THEM OUT!</description>
				<baseMoodEffect>-40</baseMoodEffect>
			</li>
		</stages>
	</ThoughtDef>
</Defs>